pyramid/__init__.py
pyramid/asset.py
pyramid/authentication.py
pyramid/authorization.py
pyramid/csrf.py
pyramid/decorator.py
pyramid/encode.py
pyramid/events.py
pyramid/exceptions.py
pyramid/httpexceptions.py
pyramid/i18n.py
pyramid/interfaces.py
pyramid/location.py
pyramid/paster.py
pyramid/path.py
pyramid/predicates.py
pyramid/registry.py
pyramid/renderers.py
pyramid/request.py
pyramid/resource.py
pyramid/response.py
pyramid/router.py
pyramid/scripting.py
pyramid/security.py
pyramid/session.py
pyramid/settings.py
pyramid/static.py
pyramid/testing.py
pyramid/threadlocal.py
pyramid/traversal.py
pyramid/tweens.py
pyramid/url.py
pyramid/urldispatch.py
pyramid/util.py
pyramid/view.py
pyramid/viewderivers.py
pyramid/wsgi.py
pyramid/config/__init__.py
pyramid/config/actions.py
pyramid/config/adapters.py
pyramid/config/assets.py
pyramid/config/factories.py
pyramid/config/i18n.py
pyramid/config/predicates.py
pyramid/config/rendering.py
pyramid/config/routes.py
pyramid/config/security.py
pyramid/config/settings.py
pyramid/config/testing.py
pyramid/config/tweens.py
pyramid/config/views.py
pyramid/config/zca.py
pyramid/scripts/__init__.py
pyramid/scripts/common.py
pyramid/scripts/pdistreport.py
pyramid/scripts/prequest.py
pyramid/scripts/proutes.py
pyramid/scripts/pserve.py
pyramid/scripts/pshell.py
pyramid/scripts/ptweens.py
pyramid/scripts/pviews.py
pyramid-2.0.1.dist-info/LICENSE.txt
pyramid-2.0.1.dist-info/METADATA
pyramid-2.0.1.dist-info/WHEEL
pyramid-2.0.1.dist-info/entry_points.txt
pyramid-2.0.1.dist-info/top_level.txt
pyramid-2.0.1.dist-info/RECORD
