Metadata-Version: 2.1
Name: pyramid
Version: 2.0.1
Summary: The Pyramid Web Framework, a Pylons project
Home-page: https://trypyramid.com
Author: Chris McDonough, Agendaless Consulting
Author-email: pylons-discuss@googlegroups.com
License: BSD-derived (Repoze)
Project-URL: Documentation, https://docs.pylonsproject.org/projects/pyramid/en/2.0-branch/
Project-URL: Changelog, https://docs.pylonsproject.org/projects/pyramid/en/2.0-branch/whatsnew-2.0.html
Project-URL: Issue Tracker, https://github.com/Pylons/pyramid/issues
Keywords: web,wsgi,pylons,pyramid
Classifier: Development Status :: 6 - Mature
Classifier: Intended Audience :: Developers
Classifier: Programming Language :: Python
Classifier: Programming Language :: Python :: 3
Classifier: Programming Language :: Python :: 3.6
Classifier: Programming Language :: Python :: 3.7
Classifier: Programming Language :: Python :: 3.8
Classifier: Programming Language :: Python :: 3.9
Classifier: Programming Language :: Python :: 3.10
Classifier: Programming Language :: Python :: 3.11
Classifier: Programming Language :: Python :: Implementation :: CPython
Classifier: Programming Language :: Python :: Implementation :: PyPy
Classifier: Framework :: Pyramid
Classifier: Topic :: Internet :: WWW/HTTP
Classifier: Topic :: Internet :: WWW/HTTP :: WSGI
Classifier: License :: Repoze Public License
Requires-Python: >=3.6
Provides-Extra: testing
Provides-Extra: docs
License-File: LICENSE.txt
